kungfupanda/__init__.py
kungfupanda/kungfupanda.py
kungfupanda/resources/gif_1.gif
kungfupanda-0.26.dist-info/METADATA
kungfupanda-0.26.dist-info/WHEEL
kungfupanda-0.26.dist-info/top_level.txt
kungfupanda-0.26.dist-info/RECORD
