Metadata-Version: 2.1
Name: kungfupanda
Version: 0.26
Summary: A simple package to make everything easy for programmers to do everything the cool way
Home-page: 
Author: The Big Fat Panda
Author-email: po_the_big_fat_panda@gmail.com
Requires-Dist: pandas
Requires-Dist: opencv-python
